etch/__init__.py
etch/api.py
etch/instructions/__init__.py
etch/instructions/operators.py
etch/mixins/__init__.py
etch/parser/lexer.py
etch/parser/parser.py
etch/stdlib/__init__.py
etch/stdlib/json.py
etch/stdlib/net.py
etch/stdlib/rand.py
etch/stdlib/str.py
etch/utils.py
etchlang-0.2.3.dist-info/WHEEL
etchlang-0.2.3.dist-info/METADATA
etchlang-0.2.3.dist-info/RECORD
